tests/test_tree_classifier.py
tests/test_forest.py
tests/test_layer_estimator.py
tests/test_io.py
tests/test_model_input.py
tests/test_model_classifier.py
tests/test_tree regressor.py
tests/test_binner.py
tests/test_utils.py
tests/test_set_custom_estimator.py
tests/test_tree_same.py
tests/__init__.py
tests/test_buffer.py
tests/test_model_regressor.py
deep_forest-0.1.6.dist-info/top_level.txt
deep_forest-0.1.6.dist-info/WHEEL
deep_forest-0.1.6.dist-info/METADATA
deep_forest-0.1.6.dist-info/RECORD
deep_forest-0.1.6.dist-info/LICENSE
deepforest/_layer.py
deepforest/setup.py
deepforest/_estimator.py
deepforest/_forest.cpython-37m-x86_64-linux-gnu.so
deepforest/_binner.py
deepforest/forest.py
deepforest/cascade.py
deepforest/__init__.py
deepforest/_cutils.cpython-37m-x86_64-linux-gnu.so
deepforest/_utils.py
deepforest/_io.py
deepforest/tree/setup.py
deepforest/tree/_tree.cpython-37m-x86_64-linux-gnu.so
deepforest/tree/_criterion.cpython-37m-x86_64-linux-gnu.so
deepforest/tree/tree.py
deepforest/tree/_utils.cpython-37m-x86_64-linux-gnu.so
deepforest/tree/_splitter.cpython-37m-x86_64-linux-gnu.so
deepforest/tree/__init__.py
deepforest/utils/kfoldwrapper.py
deepforest/utils/__init__.py
