Metadata-Version: 2.1
Name: deep-forest
Version: 0.1.6
Summary: Deep Forest
Home-page: https://github.com/LAMDA-NJU/Deep-Forest
Maintainer: Yi-Xuan Xu
Maintainer-email: xuyx@lamda.nju.edu.cn
Classifier: Intended Audience :: Science/Research
Classifier: Intended Audience :: Developers
Classifier: Programming Language :: Python
Classifier: Topic :: Software Development
Classifier: Topic :: Scientific/Engineering
Classifier: Operating System :: Microsoft :: Windows
Classifier: Operating System :: Unix
Classifier: Programming Language :: Python :: 3.7
Classifier: Programming Language :: Python :: 3.8
Classifier: Programming Language :: Python :: 3.9
Requires-Python: >=3.7
License-File: LICENSE
Requires-Dist: numpy (>=1.14.6)
Requires-Dist: scipy (>=1.1.0)
Requires-Dist: joblib (>=0.11)
Requires-Dist: scikit-learn (>=1.0)
